[
  {
    "name": "덕수궁",
    "category": "궁궐",
    "location": "서울 중구 세종대로 99",
    "summary": "덕수궁은 조선 시대 궁궐 중 하나로, 대한제국 시기 고종 황제가 머물렀던 장소입니다.",
    "background": "덕수궁은 조선 후기와 대한제국 시기의 역사가 함께 남아 있는 궁궐입니다. 특히 고종이 대한제국을 선포한 이후 근대 국가로 나아가려던 시기의 분위기를 보여줍니다.",
    "history": [
      "원래는 왕족의 사저였으나 임진왜란 이후 선조가 머물면서 궁궐로 사용되기 시작했습니다.",
      "대한제국 시기에는 고종 황제가 머물며 근대화를 추진하던 공간이었습니다.",
      "전통 궁궐 건축과 서양식 건축인 석조전이 함께 남아 있습니다."
    ],
    "episodes": [
      "석조전은 대한제국이 서양식 근대 국가의 모습을 갖추려 했던 흔적으로 볼 수 있습니다.",
      "덕수궁 돌담길은 오늘날 산책 명소지만, 근대 서울의 분위기가 남아 있는 길이기도 합니다."
    ],
    "view_points": [
      "대한문",
      "중화전",
      "석조전",
      "덕수궁 돌담길"
    ],
    "keywords": ["조선", "대한제국", "고종", "석조전", "정동"]
  }
]